rlimit/__init__.py
rlimit/base_limiter.py
rlimit/expiringdict_memory.py
rlimit/memory_abc.py
rlimit/per.py
rlimit-1.5.dist-info/LICENSE
rlimit-1.5.dist-info/METADATA
rlimit-1.5.dist-info/WHEEL
rlimit-1.5.dist-info/top_level.txt
rlimit-1.5.dist-info/RECORD
