Metadata-Version: 2.1
Name: rlimit
Version: 1.5
Summary: python rate limiter
Author-email: omidekz <omidekz@gmail.com>
Project-URL: Homepage, https://github.com/omidekz/rlimit
Project-URL: Bug Tracker, https://github.com/omidekz/rlimit/issues
Classifier: Programming Language :: Python :: 3
Classifier: Operating System :: OS Independent
Requires-Python: >=3.7
License-File: LICENSE
